{
  "title":"How to Crochet an Amigurumi Toy",
  "url":"https://www.wikihow.com/Crochet-an-Amigurumi-Toy",
  "category_hierarchy":[
    "Hobbies and Crafts",
    "Crafts",
    "Needlework",
    "Knitting and Crochet",
    "Crochet"
  ],
  "methods":[
    {
      "name":"Head\\/Body",
      "steps":[
        {
          "headline":"With light blue yarn:",
          "description":"Rnd 1 : Ch 2. 6 sc in 2nd ch from hook. (6 sc)\nRnd 2 : Work 2 sc in each sc around. (12 sc)\nRnd 3 : [sc in next sc, 2 sc in next sc] 6 times. (18 sc)\nRnd 4 : [sc in next 2 sc, 2 sc in next sc] 6 times. (24 sc)\nRnd 5 : [sc in next 3 sc, 2 sc in next sc] 6 times. (30 sc)\nRnd 6 : [sc in next 4 sc, 2 sc in next sc] 6 times. (36 sc)\nRnd 7 : [sc in next 5 sc, 2 sc in next sc] 6 times. (42 sc)\nRnd 8 : [sc in next 6 sc, 2 sc in next sc] 6 times. (48 sc)\nRnd 9 to 16 : Sc in each sc around. (48 sc)"
        },
        {
          "headline":"Now for the decreasing rounds:",
          "description":"Rnd 17 : [sc in each of next 6 sc, dec 1 sc over next 2 sc] 6 times. (42 sc)\nRnd 18 : [sc in each of next 5 sc, dec 1 sc over next 2 sc] 6 times. (36 sc)\nRnd 19 : [sc in each of next 4 sc, dec 1 sc over next 2 sc] 6 times. (30 sc)\nRnd 20 to 22 : Sc in each sc around. (30 sc)"
        },
        {
          "headline":"Now for the increasing rounds:",
          "description":"Rnd 23 : [sc in next 4 sc, 2 sc in next sc] 6 times. (36 sc)\nRnd 24 : [sc in next 5 sc, 2 sc in next sc] 6 times. (42 sc)\nRnd 25 to 28 : Sc in each sc around. (42 sc)"
        },
        {
          "headline":"Now for the decreasing rounds:",
          "description":"Rnd 29 : [sc in each of next 5 sc, dec 1 sc over next 2 sc] 6 times. (36 sc)\nRnd 30 : [sc in each of next 4 sc, dec 1 sc over next 2 sc] 6 times. (30 sc)\nRnd 31 : [sc in each of next 3 sc, dec 1 sc over next 2 sc] 6 times. (24 sc)"
        },
        {
          "headline":"At this point, change to dark blue yarn and continue decreasing:",
          "description":"Rnd 32 : [sc in each of next 2 sc, dec 1 sc over next 2 sc] 6times. (18 sc)"
        },
        {
          "headline":"Stuff body/head with polyfill:",
          "description":"Rnd 33 : [sc in next sc, dec 1 sc over next 2 sc] 6 times. (12 sc)\nRnd 34 : [Dec 1 sc over next 2 sc] 6 times. (6 sc)"
        },
        {
          "headline":"At the end of round 34, sl st in next sc leaving a length of yarn, fasten off.",
          "description":""
        },
        {
          "headline":"With tapestry needle, weave in remaining length through sc of rnd 34, pull to close opening, secure and fasten off.",
          "description":""
        }
      ]
    },
    {
      "name":"Pointy Locks (make 5 pieces)",
      "steps":[
        {
          "headline":"With dark blue yarn and leaving a length of yarn for sewing later, make 5 similar pieces as follows.",
          "description":""
        },
        {
          "headline":"Working in rows:",
          "description":"Row 1 : Ch 5. Sc in 2nd ch from hook and in each ch throughout. (4 sc). Ch1, turn. Row 2 & 3 : 4sc. Ch1, turn. Row 5 : [dec 1 sc over next 2 sc] 2 times. (2 sc). Ch 1, turn. Row 6 & 7 : 2sc. Ch 1, turn. Row 8 : Dec 1 sc over next 2 sc. (1 sc). Ch 1, turn. Row 9 & 10 : 1 sc. Ch 1, turn. Fasten off."
        },
        {
          "headline":"Thread the beginning length of yarn through a tapestry needle and sew each piece of lock around the circumference of the dark blue patch on the top of the head.",
          "description":""
        }
      ]
    },
    {
      "name":"Feet (make 2)",
      "steps":[
        {
          "headline":"With orange yarn and leaving a length of yarn for sewing later, make 2 similar pieces as follows.",
          "description":""
        },
        {
          "headline":"Working in rows:",
          "description":"Row 1 : Ch 7. Sc in 2nd ch from hook and in each ch throughout. (6 sc). Ch1, turn. Row 2 : 6 sc. Ch1, turn. Row 3 : [ dec 1 sc over next 2 sc]3 times. (3 sc). Ch 1, turn. Row 4 : 3 sc. Ch 1, turn. Row 5 : Dec to 1 sc. Fasten off."
        },
        {
          "headline":"Thread the beginning length of yarn through a tapestry needle and sew each foot to bottom of body, aligning them next to each other.",
          "description":""
        }
      ]
    },
    {
      "name":"Eyes (make 2)",
      "steps":[
        {
          "headline":"With off-white yarn:",
          "description":"Rnd 1 : Ch 2. 6 sc in 2nd ch from hook. (6 sc)\nRnd 2 : Work 2 sc in each sc around. (12 sc)"
        },
        {
          "headline":"Sl st to beginning sc and fasten off, leaving a length of yarn for sewing eye onto face.",
          "description":""
        },
        {
          "headline":"Sew 2 big french knots using black yarn into the centre of the off-white eye patches.",
          "description":""
        }
      ]
    },
    {
      "name":"Finishing",
      "steps":[
        {
          "headline":"Thread neon pink yarn through a tapestry needle.",
          "description":"Embroider a heart-shaped mouth (or any other shape that you prefer) onto the face."
        },
        {
          "headline":"Sit back and enjoy the finished toy!",
          "description":"{\"smallUrl\":\"https:\\/\\/www.wikihow.com\\/images\\/1\\/1a\\/Ami1_812.JPG\",\"bigUrl\":\"https:\\/\\/www.wikihow.com\\/images\\/1\\/1a\\/Ami1_812.JPG\",\"smallWidth\":460,\"smallHeight\":651,\"bigWidth\":760,\"bigHeight\":1074.7474747474748,\"licensing\":\"<div class=\\\"mw-parser-output\\\"><p>License: <a rel=\\\"nofollow\\\" class=\\\"external text\\\" href=\\\"https:\\/\\/creativecommons.org\\/licenses\\/by\\/2.5\\/\\\">Creative Commons<\\/a><br>\\n<\\/p><\\/div>\"}"
        }
      ]
    }
  ],
  "text":" Head\\/Body With light blue yarn: Rnd 1 : Ch 2. 6 sc in 2nd ch from hook. (6 sc)\nRnd 2 : Work 2 sc in each sc around. (12 sc)\nRnd 3 : [sc in next sc, 2 sc in next sc] 6 times. (18 sc)\nRnd 4 : [sc in next 2 sc, 2 sc in next sc] 6 times. (24 sc)\nRnd 5 : [sc in next 3 sc, 2 sc in next sc] 6 times. (30 sc)\nRnd 6 : [sc in next 4 sc, 2 sc in next sc] 6 times. (36 sc)\nRnd 7 : [sc in next 5 sc, 2 sc in next sc] 6 times. (42 sc)\nRnd 8 : [sc in next 6 sc, 2 sc in next sc] 6 times. (48 sc)\nRnd 9 to 16 : Sc in each sc around. (48 sc) Now for the decreasing rounds: Rnd 17 : [sc in each of next 6 sc, dec 1 sc over next 2 sc] 6 times. (42 sc)\nRnd 18 : [sc in each of next 5 sc, dec 1 sc over next 2 sc] 6 times. (36 sc)\nRnd 19 : [sc in each of next 4 sc, dec 1 sc over next 2 sc] 6 times. (30 sc)\nRnd 20 to 22 : Sc in each sc around. (30 sc) Now for the increasing rounds: Rnd 23 : [sc in next 4 sc, 2 sc in next sc] 6 times. (36 sc)\nRnd 24 : [sc in next 5 sc, 2 sc in next sc] 6 times. (42 sc)\nRnd 25 to 28 : Sc in each sc around. (42 sc) Now for the decreasing rounds: Rnd 29 : [sc in each of next 5 sc, dec 1 sc over next 2 sc] 6 times. (36 sc)\nRnd 30 : [sc in each of next 4 sc, dec 1 sc over next 2 sc] 6 times. (30 sc)\nRnd 31 : [sc in each of next 3 sc, dec 1 sc over next 2 sc] 6 times. (24 sc) At this point, change to dark blue yarn and continue decreasing: Rnd 32 : [sc in each of next 2 sc, dec 1 sc over next 2 sc] 6times. (18 sc) Stuff body/head with polyfill: Rnd 33 : [sc in next sc, dec 1 sc over next 2 sc] 6 times. (12 sc)\nRnd 34 : [Dec 1 sc over next 2 sc] 6 times. (6 sc) At the end of round 34, sl st in next sc leaving a length of yarn, fasten off.  With tapestry needle, weave in remaining length through sc of rnd 34, pull to close opening, secure and fasten off.  Pointy Locks (make 5 pieces) With dark blue yarn and leaving a length of yarn for sewing later, make 5 similar pieces as follows.  Working in rows: Row 1 : Ch 5. Sc in 2nd ch from hook and in each ch throughout. (4 sc). Ch1, turn. Row 2 & 3 : 4sc. Ch1, turn. Row 5 : [dec 1 sc over next 2 sc] 2 times. (2 sc). Ch 1, turn. Row 6 & 7 : 2sc. Ch 1, turn. Row 8 : Dec 1 sc over next 2 sc. (1 sc). Ch 1, turn. Row 9 & 10 : 1 sc. Ch 1, turn. Fasten off. Thread the beginning length of yarn through a tapestry needle and sew each piece of lock around the circumference of the dark blue patch on the top of the head.  Feet (make 2) With orange yarn and leaving a length of yarn for sewing later, make 2 similar pieces as follows.  Working in rows: Row 1 : Ch 7. Sc in 2nd ch from hook and in each ch throughout. (6 sc). Ch1, turn. Row 2 : 6 sc. Ch1, turn. Row 3 : [ dec 1 sc over next 2 sc]3 times. (3 sc). Ch 1, turn. Row 4 : 3 sc. Ch 1, turn. Row 5 : Dec to 1 sc. Fasten off. Thread the beginning length of yarn through a tapestry needle and sew each foot to bottom of body, aligning them next to each other.  Eyes (make 2) With off-white yarn: Rnd 1 : Ch 2. 6 sc in 2nd ch from hook. (6 sc)\nRnd 2 : Work 2 sc in each sc around. (12 sc) Sl st to beginning sc and fasten off, leaving a length of yarn for sewing eye onto face.  Sew 2 big french knots using black yarn into the centre of the off-white eye patches.  Finishing Thread neon pink yarn through a tapestry needle. Embroider a heart-shaped mouth (or any other shape that you prefer) onto the face. Sit back and enjoy the finished toy! {\"smallUrl\":\"https:\\/\\/www.wikihow.com\\/images\\/1\\/1a\\/Ami1_812.JPG\",\"bigUrl\":\"https:\\/\\/www.wikihow.com\\/images\\/1\\/1a\\/Ami1_812.JPG\",\"smallWidth\":460,\"smallHeight\":651,\"bigWidth\":760,\"bigHeight\":1074.7474747474748,\"licensing\":\"<div class=\\\"mw-parser-output\\\"><p>License: <a rel=\\\"nofollow\\\" class=\\\"external text\\\" href=\\\"https:\\/\\/creativecommons.org\\/licenses\\/by\\/2.5\\/\\\">Creative Commons<\\/a><br>\\n<\\/p><\\/div>\"}",
  "sentences":[
    " Head\\/Body With light blue yarn: Rnd 1 : Ch 2.",
    "6 sc in 2nd ch from hook.",
    "(6 sc)\nRnd 2 : Work 2 sc in each sc around.",
    "(12 sc)\nRnd 3 : [sc in next sc, 2 sc in next sc] 6 times.",
    "(18 sc)\nRnd 4 : [sc in next 2 sc, 2 sc in next sc] 6 times.",
    "(24 sc)\nRnd 5 : [sc in next 3 sc, 2 sc in next sc] 6 times.",
    "(30 sc)\nRnd 6 : [sc in next 4 sc, 2 sc in next sc] 6 times.",
    "(36 sc)\nRnd 7 : [sc in next 5 sc, 2 sc in next sc] 6 times.",
    "(42 sc)\nRnd 8 : [sc in next 6 sc, 2 sc in next sc] 6 times.",
    "(48 sc)\nRnd 9 to 16 : Sc in each sc around.",
    "(48 sc) Now for the decreasing rounds: Rnd 17 : [sc in each of next 6 sc, dec 1 sc over next 2 sc] 6 times.",
    "(42 sc)\nRnd 18 : [sc in each of next 5 sc, dec 1 sc over next 2 sc] 6 times.",
    "(36 sc)\nRnd 19 : [sc in each of next 4 sc, dec 1 sc over next 2 sc] 6 times.",
    "(30 sc)\nRnd 20 to 22 : Sc in each sc around.",
    "(30 sc) Now for the increasing rounds: Rnd 23 : [sc in next 4 sc, 2 sc in next sc] 6 times.",
    "(36 sc)\nRnd 24 : [sc in next 5 sc, 2 sc in next sc] 6 times.",
    "(42 sc)\nRnd 25 to 28 : Sc in each sc around.",
    "(42 sc) Now for the decreasing rounds: Rnd 29 : [sc in each of next 5 sc, dec 1 sc over next 2 sc] 6 times.",
    "(36 sc)\nRnd 30 : [sc in each of next 4 sc, dec 1 sc over next 2 sc] 6 times.",
    "(30 sc)\nRnd 31 : [sc in each of next 3 sc, dec 1 sc over next 2 sc] 6 times.",
    "(24 sc) At this point, change to dark blue yarn and continue decreasing: Rnd 32 : [sc in each of next 2 sc, dec 1 sc over next 2 sc] 6times.",
    "(18 sc) Stuff body/head with polyfill: Rnd 33 : [sc in next sc, dec 1 sc over next 2 sc] 6 times.",
    "(12 sc)\nRnd 34 : [Dec 1 sc over next 2 sc] 6 times.",
    "(6 sc) At the end of round 34, sl st in next sc leaving a length of yarn, fasten off.",
    "With tapestry needle, weave in remaining length through sc of rnd 34, pull to close opening, secure and fasten off.",
    "Pointy Locks (make 5 pieces) With dark blue yarn and leaving a length of yarn for sewing later, make 5 similar pieces as follows.",
    "Working in rows: Row 1 : Ch 5.",
    "Sc in 2nd ch from hook and in each ch throughout.",
    "(4 sc).",
    "Ch1, turn.",
    "Row 2 & 3 : 4sc.",
    "Ch1, turn.",
    "Row 5 : [dec 1 sc over next 2 sc] 2 times.",
    "(2 sc).",
    "Ch 1, turn.",
    "Row 6 & 7 : 2sc.",
    "Ch 1, turn.",
    "Row 8 : Dec 1 sc over next 2 sc.",
    "(1 sc).",
    "Ch 1, turn.",
    "Row 9 & 10 : 1 sc.",
    "Ch 1, turn.",
    "Fasten off.",
    "Thread the beginning length of yarn through a tapestry needle and sew each piece of lock around the circumference of the dark blue patch on the top of the head.",
    "Feet (make 2) With orange yarn and leaving a length of yarn for sewing later, make 2 similar pieces as follows.",
    "Working in rows: Row 1 : Ch 7.",
    "Sc in 2nd ch from hook and in each ch throughout.",
    "(6 sc).",
    "Ch1, turn.",
    "Row 2 : 6 sc.",
    "Ch1, turn.",
    "Row 3 : [ dec 1 sc over next 2 sc]3 times.",
    "(3 sc).",
    "Ch 1, turn.",
    "Row 4 : 3 sc.",
    "Ch 1, turn.",
    "Row 5 : Dec to 1 sc.",
    "Fasten off.",
    "Thread the beginning length of yarn through a tapestry needle and sew each foot to bottom of body, aligning them next to each other.",
    "Eyes (make 2) With off-white yarn: Rnd 1 : Ch 2.",
    "6 sc in 2nd ch from hook.",
    "(6 sc)\nRnd 2 : Work 2 sc in each sc around.",
    "(12 sc) Sl st to beginning sc and fasten off, leaving a length of yarn for sewing eye onto face.",
    "Sew 2 big french knots using black yarn into the centre of the off-white eye patches.",
    "Finishing Thread neon pink yarn through a tapestry needle.",
    "Embroider a heart-shaped mouth (or any other shape that you prefer) onto the face.",
    "Sit back and enjoy the finished toy!",
    "{\"smallUrl\":\"https:\\/\\/www.wikihow.com\\/images\\/1\\/1a\\/Ami1_812.JPG\",\"bigUrl\":\"https:\\/\\/www.wikihow.com\\/images\\/1\\/1a\\/Ami1_812.JPG\",\"smallWidth\":460,\"smallHeight\":651,\"bigWidth\":760,\"bigHeight\":1074.7474747474748,\"licensing\":\"<div class=\\\"mw-parser-output\\\"><p>License: <a rel=\\\"nofollow\\\" class=\\\"external text\\\" href=\\\"https:\\/\\/creativecommons.org\\/licenses\\/by\\/2.5\\/\\\">Creative Commons<\\/a><br>\\n<\\/p><\\/div>\"}"
  ],
  "tyn_section":[
    "Acrylic Yarn (light blue, dark blue, orange, black, neon pink and off-white)",
    "Polyfill",
    "Tapestry/yarn needle",
    "Crochet hook (one size smaller than the size needed for your yarn type)",
    "A pair of scissors"
  ],
  "tyn_model":[
    "yarn",
    "tapestry needle",
    "sc",
    "polyfill",
    "sl",
    "orange yarn",
    "neon pink yarn"
  ],
  "simple_metrics":{
    "r":0.2,
    "p":0.1428571429,
    "f1":0.1666666667,
    "avg_pos":0
  },
  "jacc_metrics_0.5":{
    "r":0.2,
    "p":0.1428571429,
    "f1":0.1666666667
  },
  "jacc_metrics_0.3333333333333333":{
    "r":0.4,
    "p":0.2857142857,
    "f1":0.3333333333
  },
  "jacc_metrics_0.6666666666666666":{
    "r":0.2,
    "p":0.1428571429,
    "f1":0.1666666667
  }
}